<?xml version="1.0" encoding="utf-8" ?>
<Body>
  <CityStation>
    <field>北京</field>
    <field>天津</field>
    <field>石家庄</field>
    <field>唐山</field>
    <field>秦皇岛</field>
    <field>邯郸</field>
    <field>保定</field>
    <field>太原</field>
    <field>大同</field>
    <field>阳泉</field>
    <field>长治</field>
    <field>临汾</field>
    <field>呼和浩特</field>
    <field>包头</field>
    <field>赤峰</field>
    <field>沈阳</field>
    <field>大连</field>
    <field>鞍山</field>
    <field>抚顺</field>
    <field>本溪</field>
    <field>锦州</field>
    <field>长春</field>
    <field>吉林</field>
    <field>哈尔滨</field>
    <field>大庆</field>
    <field>齐齐哈尔</field>
    <field>牡丹江</field>
    <field>上海</field>
    <field>南京</field>
    <field>无锡</field>
    <field>徐州</field>
    <field>常州</field>
    <field>苏州</field>
    <field>南通</field>
    <field>连云港</field>
    <field>扬州</field>
    <field>镇江</field>
    <field>杭州</field>
    <field>嘉兴</field>
    <field>台州</field>
    <field>宁波</field>
    <field>温州</field>
    <field>湖州</field>
    <field>绍兴</field>
    <field>合肥</field>
    <field>芜湖</field>
    <field>马鞍山</field>
    <field>福州</field>
    <field>厦门</field>
    <field>泉州</field>
    <field>南昌</field>
    <field>九江</field>
    <field>济南</field>
    <field>青岛</field>
    <field>淄博</field>
    <field>枣庄</field>
    <field>烟台</field>
    <field>潍坊</field>
    <field>济宁</field>
    <field>泰安</field>
    <field>日照</field>
    <field>威海</field>
    <field>郑州</field>
    <field>开封</field>
    <field>洛阳</field>
    <field>平顶山</field>
    <field>安阳</field>
    <field>焦作</field>
    <field>三门峡</field>
    <field>武汉</field>
    <field>宜昌</field>
    <field>荆州</field>
    <field>长沙</field>
    <field>株洲</field>
    <field>湘潭</field>
    <field>岳阳</field>
    <field>常德</field>
    <field>张家界</field>
    <field>广州</field>
    <field>佛山</field>
    <field>韶关</field>
    <field>深圳</field>
    <field>珠海</field>
    <field>汕头</field>
    <field>中山</field>
    <field>湛江</field>
    <field>南宁</field>
    <field>柳州</field>
    <field>桂林</field>
    <field>北海</field>
    <field>海口</field>
    <field>三亚</field>
    <field>重庆</field>
    <field>成都</field>
    <field>自贡</field>
    <field>攀枝花</field>
    <field>泸州</field>
    <field>德阳</field>
    <field>绵阳</field>
    <field>南充</field>
    <field>宜宾</field>
    <field>贵阳</field>
    <field>遵义</field>
    <field>昆明</field>
    <field>曲靖</field>
    <field>玉溪</field>
    <field>拉萨</field>
    <field>西安</field>
    <field>铜川</field>
    <field>宝鸡</field>
    <field>咸阳</field>
    <field>渭南</field>
    <field>延安</field>
    <field>兰州</field>
    <field>金昌</field>
    <field>西宁</field>
    <field>银川</field>
    <field>石嘴山</field>
    <field>乌鲁木齐</field>
    <field>克拉玛依</field>
  </CityStation>
</Body>
